{
	"name": "Pipeline-Cotacao_Dolar",
	"properties": {
		"activities": [
			{
				"name": "Camada_Bronze",
				"type": "Copy",
				"dependsOn": [],
				"policy": {
					"timeout": "0.12:00:00",
					"retry": 0,
					"retryIntervalInSeconds": 30,
					"secureOutput": false,
					"secureInput": false
				},
				"userProperties": [],
				"typeProperties": {
					"source": {
						"type": "ParquetSource",
						"storeSettings": {
							"type": "HttpReadSettings",
							"requestMethod": "GET"
						},
						"formatSettings": {
							"type": "ParquetReadSettings"
						}
					},
					"sink": {
						"type": "DelimitedTextSink",
						"storeSettings": {
							"type": "AzureBlobFSWriteSettings"
						},
						"formatSettings": {
							"type": "DelimitedTextWriteSettings",
							"quoteAllText": true,
							"fileExtension": ".txt"
						}
					},
					"enableStaging": false
				}
			},
			{
				"name": "Camada_Silver",
				"type": "DatabricksNotebook",
				"dependsOn": [
					{
						"activity": "Camada_Bronze",
						"dependencyConditions": [
							"Succeeded"
						]
					}
				],
				"policy": {
					"timeout": "0.12:00:00",
					"retry": 0,
					"retryIntervalInSeconds": 30,
					"secureOutput": false,
					"secureInput": false
				},
				"userProperties": [],
				"typeProperties": {
					"notebookPath": "/Users/kleber-goes@hotmail.com/Pipeline-Cotacao-Dolar-Azure_Databricks/Arquitetura_Medalhao/1. Camada Silver"
				},
				"linkedServiceName": {
					"referenceName": "AzureDatabricksConexao",
					"type": "LinkedServiceReference"
				}
			},
			{
				"name": "Camada_Gold",
				"type": "DatabricksNotebook",
				"dependsOn": [
					{
						"activity": "Camada_Silver",
						"dependencyConditions": [
							"Succeeded"
						]
					}
				],
				"policy": {
					"timeout": "0.12:00:00",
					"retry": 0,
					"retryIntervalInSeconds": 30,
					"secureOutput": false,
					"secureInput": false
				},
				"userProperties": [],
				"typeProperties": {
					"notebookPath": "/Users/kleber-goes@hotmail.com/Pipeline-Cotacao-Dolar-Azure_Databricks/Arquitetura_Medalhao/2. Camada Gold"
				},
				"linkedServiceName": {
					"referenceName": "AzureDatabricksConexao",
					"type": "LinkedServiceReference"
				}
			}
		],
		"folder": {
			"name": "Pipeline_Cotacao_Dolar"
		},
		"annotations": []
	}
}